github_email_scraper/__init__.py
github_email_scraper/github_email_scraper.py
github_email_scraper-1.0.0.dist-info/LICENSE
github_email_scraper-1.0.0.dist-info/METADATA
github_email_scraper-1.0.0.dist-info/WHEEL
github_email_scraper-1.0.0.dist-info/entry_points.txt
github_email_scraper-1.0.0.dist-info/top_level.txt
github_email_scraper-1.0.0.dist-info/RECORD
