Metadata-Version: 2.1
Name: github-email-scraper
Version: 1.0.0
Summary: Scrape GitHub to get user emails
Home-page: https://github.com/andyjsmith/GitHub-Email-Scraper
Author: Andy Smith
License: UNKNOWN
Keywords: scraper,github,email,crawler
Platform: UNKNOWN
Classifier: Programming Language :: Python :: 3
Classifier: Programming Language :: Python :: 3.6
Classifier: Programming Language :: Python :: 3.7
Classifier: Programming Language :: Python :: 3.8
Classifier: Programming Language :: Python :: 3.9
Classifier: License :: OSI Approved :: Apache Software License
Classifier: Operating System :: OS Independent
Classifier: Environment :: Console
Requires-Python: >=3.6
Requires-Dist: requests
